Metadata-Version: 2.1
Name: dox-docs-translator
Version: 0.1.1
Summary: Translator of custom Doxygen-documentation
Home-page: https://github.com/Nakama3942/dox_docs_translator
Author: Kalynovsky 'Nakama3942' Valentin
Author-email: nakama3942@gmail.com
License: Apache License, Version 2.0, see LICENSE file
Platform: UNKNOWN
Classifier: License :: OSI Approved :: Apache Software License
Classifier: Operating System :: OS Independent
Classifier: Programming Language :: Python :: 3.10
License-File: LICENSE
